QCANT/QCANT.py
QCANT/__init__.py
QCANT/_version.py
QCANT/py.typed
QCANT/adapt/__init__.py
QCANT/adapt/adaptvqe.py
QCANT/qrte/__init__.py
QCANT/qrte/qrte.py
QCANT/qsceom/__init__.py
QCANT/qsceom/excitations.py
QCANT/qsceom/qsceom.py
QCANT/tests/__init__.py
QCANT/tests/test_QCANT.py
QCANT/tests/test_algorithms_integration_h2.py
QCANT/tests/test_algorithms_optional_deps.py
QCANT/tests/test_qrte_h2.py
qcant-1.0.0.dist-info/licenses/LICENSE
qcant-1.0.0.dist-info/METADATA
qcant-1.0.0.dist-info/WHEEL
qcant-1.0.0.dist-info/top_level.txt
qcant-1.0.0.dist-info/RECORD
