Metadata-Version: 2.4
Name: QCANT
Version: 1.0.0
Summary: A set of codes useful for near term applications of quantum computing in chemistry and materials science
Author-email: SRIVATHSAN P SUNDAR <sundarbalaji4@gmail.com>
License-Expression: BSD-3-Clause
Project-URL: Homepage, https://github.com/srivathsanps-quantum/QCANT
Project-URL: Source, https://github.com/srivathsanps-quantum/QCANT
Project-URL: Documentation, https://srivathsanps-quantum.github.io/QCANT/
Classifier: Development Status :: 3 - Alpha
Classifier: Intended Audience :: Science/Research
Classifier: Operating System :: OS Independent
Classifier: Programming Language :: Python :: 3
Classifier: Programming Language :: Python :: 3 :: Only
Classifier: Programming Language :: Python :: 3.9
Classifier: Programming Language :: Python :: 3.10
Classifier: Programming Language :: Python :: 3.11
Classifier: Programming Language :: Python :: 3.12
Classifier: Topic :: Scientific/Engineering :: Chemistry
Classifier: Typing :: Typed
Requires-Python: >=3.8
License-File: LICENSE
Requires-Dist: numpy<2
Requires-Dist: scipy<2
Requires-Dist: pennylane
Requires-Dist: pyscf
Requires-Dist: autoray<0.7,>=0.6.11
Provides-Extra: test
Requires-Dist: pytest>=6.1.2; extra == "test"
Provides-Extra: docs
Requires-Dist: sphinx; extra == "docs"
Requires-Dist: pydata-sphinx-theme; extra == "docs"
Requires-Dist: sphinx-design; extra == "docs"
Requires-Dist: sphinx-copybutton; extra == "docs"
Dynamic: license-file
